<?xml version="1.0" encoding="UTF-8"?>
<vocabulaire l1="anglais" l2="français"><mot l1="lethal / deadly" l2="mortel"/><mot l1="a fit" l2="une crise"/><mot l1="to gasp" l2="s'asphyxier"/><mot l1="to publicize/to advertise" l2="faire de la publicité"/><mot l1="the awareness" l2="la prise de conscience"/><mot l1="to tend to" l2="tendre à"/><mot l1="to have a tendency" l2="avoir tendance"/><mot l1="wise" l2="sage"/><mot l1="wisdom" l2="sagesse"/><mot l1="awkward" l2="maladroit"/><mot l1="the crocks" l2="la vaisselle ébréchée"/><mot l1="weird/odd/strange" l2="bizarre"/><mot l1="to tear, tore, torn" l2="déchirer"/><mot l1="the oilcloth" l2="la toile cirée"/><mot l1="stale" l2="rassis"/><mot l1="a stocking" l2="un collant"/><mot l1="efficient/effective" l2="efficace"/><mot l1="the realm of" l2="le royaume de/le monde de"/><mot l1="a fad" l2="une tendance/une mode"/><mot l1="to wag" l2="remuer"/><mot l1="the sins" l2="les pêchés"/><mot l1="the sinner" l2="le pêcheur/celui qui a commis un pêché"/><mot l1="vacuum cleaner" l2="aspirateur"/><mot l1="healthy/wholesome" l2="sain"/><mot l1="the newly weds" l2="les jeunes mariés"/><mot l1="word to mouth" l2="bouche à oreille"/><mot l1="a hoax" l2="une supercherie"/><mot l1="the attic" l2="le grenier"/><mot l1="a lay-off" l2="un licenciement"/><mot l1="entertainment" l2="divertissement"/><mot l1="to bathe" l2="se baigner"/><mot l1="the plague" l2="la peste"/><mot l1="a physicist" l2="un physicien"/><mot l1="a physician" l2="un médecin"/></vocabulaire>
